{
  "CompanyHasParentOrganisation": 0.34,
  "CountryBordersCountry": 0.03,
  "CountryHasOfficialLanguage": 0.07,
  "PersonHasNumberOfChildren": 0.13,
  "PersonHasPlaceOfDeath": 0.31,
  "PersonHasProfession": 0.05,
  "PersonPlaysInstrument": 0.07,
  "PersonSpeaksLanguage": 0.15,
  "RiverBasinsCountry": 0.06,
  "SeriesHasNumberOfEpisodes": 0.07,
  "StateBordersState": 0.01,
  "BandHasMember": 0.01,
  "CityLocatedAtRiver": 0.03,
  "FootballerPlaysPosition": 0.1,
  "PersonCauseOfDeath": 0.45,
  "PersonHasAutobiography": 0,
  "PersonHasEmployer": 0.04,
  "PersonHasNoblePrize": 0.38,
  "PersonHasSpouse": 0,
  "CountryHasStates": 0.01,
  "CompoundHasParts": 0.03
}